vitex
