Metadata-Version: 2.1
Name: vitex
Version: 0.3.2
Summary: An unholy conglomeration of vim, evince, and friends for writing LaTeX
Home-page: https://github.com/cfangmeier/vitex
Author: Caleb Fangmeier
Author-email: caleb@fangmeier.tech
License: MIT
Keywords: vim LaTeX Gtk Markdown
Platform: UNKNOWN
Classifier: Development Status :: 4 - Beta
Classifier: License :: OSI Approved :: MIT License
Classifier: Intended Audience :: Developers
Classifier: Intended Audience :: End Users/Desktop
Classifier: Operating System :: Unix
Classifier: Programming Language :: Python :: 3.6
Classifier: Programming Language :: Python :: 3 :: Only
